.gitignore
LICENSE
MANIFEST.in
README.rst
requirements.txt
setup.py
test-requirements.txt
test_workq.py
tox.ini
workq.py
workq.egg-info/PKG-INFO
workq.egg-info/SOURCES.txt
workq.egg-info/dependency_links.txt
workq.egg-info/requires.txt
workq.egg-info/top_level.txt