Metadata-Version: 1.1
Name: workq
Version: 1.0.0
Summary: Iterative Work Queue
Home-page: https://github.com/klmitch/workq
Author: Kevin L. Mitchell
Author-email: klmitch@mit.edu
License: Apache License (2.0)
Platform: UNKNOWN
Classifier: Development Status :: 5 - Production/Stable
Classifier: Intended Audience :: Developers
Classifier: License :: OSI Approved :: Apache Software License
Classifier: Operating System :: OS Independent
Classifier: Programming Language :: Python
Classifier: Programming Language :: Python :: 2.6
Classifier: Programming Language :: Python :: 2.7
Classifier: Programming Language :: Python :: 3.3
Classifier: Programming Language :: Python :: 3.4
Classifier: Topic :: Utilities
